 [ {"date": "1910-02-12", "volume": "5", "issue": "2", "MODS": "../metadata/oclc_4770057679-i_49.MODS.xml", "number of pages": "72", "number of words": "19462", "number of articles": "27", "words per article": "720.8148148148148", "number of independent articles": "5", "words per independent article": "2627.8", "characters per independent article": "12141.8", "number of independent articles with author information": "2", "number of articles in sections": "22", "words per article in sections": "288.3636363636364", "characters per article in sections": "1354.7727272727273"}]